base_scrapy_project/__init__.py
base_scrapy_project/exporters.py
base_scrapy_project/items.py
base_scrapy_project/pipelines.py
base_scrapy_project/settings.py
scrapybase/__init__.py
scrapybase/exporters.py
scrapybase/items.py
scrapybase/pipelines.py
scrapybase/settings.py
scrapybase-1.2.0.dist-info/LICENSE
scrapybase-1.2.0.dist-info/METADATA
scrapybase-1.2.0.dist-info/WHEEL
scrapybase-1.2.0.dist-info/top_level.txt
scrapybase-1.2.0.dist-info/RECORD
