Metadata-Version: 2.1
Name: scrapybase
Version: 1.2.0
Summary: Base Scrapy project
Home-page: https://github.com/fdelgados/ScrapyBase.git
Author: Cisco Delgado
Author-email: fdelgados@gmail.com
License: UNKNOWN
Platform: UNKNOWN
Classifier: Programming Language :: Python :: 3
Classifier: License :: OSI Approved :: MIT License
Classifier: Operating System :: OS Independent
Requires-Python: >=3.7.3
Requires-Dist: pymongo
Requires-Dist: scrapy
